timezone_field/__init__.py
timezone_field/backends/__init__.py
timezone_field/backends/base.py
timezone_field/backends/pytz.py
timezone_field/backends/zoneinfo.py
timezone_field/choices.py
timezone_field/fields.py
timezone_field/forms.py
timezone_field/models.py
timezone_field/rest_framework.py
timezone_field/utils.py
django_timezone_field-7.2.dist-info/LICENSE.txt
django_timezone_field-7.2.dist-info/METADATA
django_timezone_field-7.2.dist-info/WHEEL
django_timezone_field-7.2.dist-info/RECORD
