Metadata-Version: 2.1
Name: django-timezone-field
Version: 7.2
Summary: A Django app providing DB, form, and REST framework fields for zoneinfo and pytz timezone objects.
Home-page: https://github.com/mfogel/django-timezone-field/
License: BSD-2-Clause
Author: Mike Fogel
Author-email: mike@fogel.ca
Requires-Python: >=3.8,<4.0
Classifier: Development Status :: 4 - Beta
Classifier: Environment :: Web Environment
Classifier: Framework :: Django
Classifier: Framework :: Django :: 4.2
Classifier: Framework :: Django :: 5.0
Classifier: Framework :: Django :: 5.1
Classifier: Framework :: Django :: 5.2
Classifier: Framework :: Django :: 6.0
Classifier: Intended Audience :: Developers
Classifier: License :: OSI Approved :: BSD License
Classifier: Operating System :: OS Independent
Classifier: Programming Language :: Python :: 3
Classifier: Programming Language :: Python :: 3.8
Classifier: Programming Language :: Python :: 3.9
Classifier: Programming Language :: Python :: 3.10
Classifier: Programming Language :: Python :: 3.11
Classifier: Programming Language :: Python :: 3.12
Classifier: Programming Language :: Python :: 3.13
Classifier: Topic :: Utilities
Requires-Dist: Django (>=3.2,<6.1)
Requires-Dist: backports.zoneinfo (>=0.2.1,<0.3.0) ; python_version < "3.9"
Project-URL: Repository, https://github.com/mfogel/django-timezone-field/
